db_manager/__init__.py
db_manager/app.py
db_manager/assets/images/data-server.png
db_manager/assets/images/hard-disk.png
db_systray-0.1.2.dist-info/METADATA
db_systray-0.1.2.dist-info/WHEEL
db_systray-0.1.2.dist-info/RECORD
