Metadata-Version: 2.1
Name: db-systray
Version: 0.1.2
Summary: 
Author: sean
Author-email: sean.li@vectorindex.cloud
Requires-Python: >=3.10,<4.0
Classifier: Programming Language :: Python :: 3
Classifier: Programming Language :: Python :: 3.10
Classifier: Programming Language :: Python :: 3.11
Classifier: Programming Language :: Python :: 3.12
Requires-Dist: litecli (>=1.13.2,<2.0.0)
Requires-Dist: omegaconf (>=2.3.0,<3.0.0)
Requires-Dist: pillow (>=11.0.0,<12.0.0)
Requires-Dist: pystray (>=0.19.5,<0.20.0)
Requires-Dist: python-dotenv (>=1.0.1,<2.0.0)
Requires-Dist: sqlite-web (>=0.6.4,<0.7.0)
